{"errors":[],"warnings":[],"namedChunkGroups":{"app":{"chunks":[6,5,2],"assets":["webpack-runtime-f92a5cbe1b2694ded450.js","webpack-runtime-f92a5cbe1b2694ded450.js.map","framework-5f60671d002a96dabc3f.js","framework-5f60671d002a96dabc3f.js.map","app-6bb04d3dffb20cecea99.js","app-6bb04d3dffb20cecea99.js.map"],"children":{},"childAssets":{}},"component---src-pages-404-js":{"chunks":[1,0,3],"assets":["styles.99d981154c3d786c092f.css","styles-f12963b3798c232a68f6.js","styles-f12963b3798c232a68f6.js.map","commons-d59f641d0089a13ad560.js","commons-d59f641d0089a13ad560.js.map","component---src-pages-404-js-c980c6cb4e100b843f1a.js","component---src-pages-404-js-c980c6cb4e100b843f1a.js.map"],"children":{},"childAssets":{}},"component---src-pages-index-js":{"chunks":[1,0,4],"assets":["styles.99d981154c3d786c092f.css","styles-f12963b3798c232a68f6.js","styles-f12963b3798c232a68f6.js.map","commons-d59f641d0089a13ad560.js","commons-d59f641d0089a13ad560.js.map","component---src-pages-index-js-7f532597ffc6bcaa6256.js","component---src-pages-index-js-7f532597ffc6bcaa6256.js.map"],"children":{},"childAssets":{}}},"assetsByChunkName":{"app":["webpack-runtime-f92a5cbe1b2694ded450.js","framework-5f60671d002a96dabc3f.js","app-6bb04d3dffb20cecea99.js"],"component---src-pages-404-js":["styles.99d981154c3d786c092f.css","styles-f12963b3798c232a68f6.js","commons-d59f641d0089a13ad560.js","component---src-pages-404-js-c980c6cb4e100b843f1a.js"],"component---src-pages-index-js":["styles.99d981154c3d786c092f.css","styles-f12963b3798c232a68f6.js","commons-d59f641d0089a13ad560.js","component---src-pages-index-js-7f532597ffc6bcaa6256.js"]}}